profane_detector/__init__.py
profane_detector/profane_detector.py
profane_detector/swear-words/ar
profane_detector/swear-words/cs
profane_detector/swear-words/da
profane_detector/swear-words/de
profane_detector/swear-words/en
profane_detector/swear-words/eo
profane_detector/swear-words/es
profane_detector/swear-words/fa
profane_detector/swear-words/fi
profane_detector/swear-words/fr
profane_detector/swear-words/fr-CA-u-sd-caqc
profane_detector/swear-words/hi
profane_detector/swear-words/hu
profane_detector/swear-words/it
profane_detector/swear-words/ja
profane_detector/swear-words/ko
profane_detector/swear-words/nl
profane_detector/swear-words/no
profane_detector/swear-words/pl
profane_detector/swear-words/pt
profane_detector/swear-words/ru
profane_detector/swear-words/sv
profane_detector/swear-words/th
profane_detector/swear-words/tlh
profane_detector/swear-words/tr
profane_detector/swear-words/zh
profane_detector/word_finder.py
profane_detector-1.1.4.dist-info/entry_points.txt
profane_detector-1.1.4.dist-info/METADATA
profane_detector-1.1.4.dist-info/WHEEL
profane_detector-1.1.4.dist-info/RECORD
