Metadata-Version: 2.1
Name: profane_detector
Version: 1.1.4
Summary: A small profane_detector
License: MIT
Author: Verso Vuorenmaa
Author-email: verso.vuorenmaa@luova.club
Requires-Python: >=3.8,<4.0
Classifier: License :: OSI Approved :: MIT License
Classifier: Programming Language :: Python :: 3
Classifier: Programming Language :: Python :: 3.8
Classifier: Programming Language :: Python :: 3.9
Classifier: Programming Language :: Python :: 3.10
Classifier: Programming Language :: Python :: 3.11
Classifier: Programming Language :: Python :: 3.12
